calcular
0 LOAD_CONST 2
1 RETURN_VALUE 
promedio
2 LOAD_CONST 2
3 LOAD_GLOBAL calcular
4 LOAD_CONST 1
5 LOAD_CONST 2
6 CALL_FUNCTION 2
7 BINARY_MULTIPLY 
8 STORE_FAST num
9 LOAD_GLOBAL print
10 LOAD_FAST num
11 CALL_FUNCTION 1
12 LOAD_CONST 1
13 LOAD_CONST 2
14 LOAD_CONST 3
15 LOAD_CONST 4
16 BUILD_LIST 
17 STORE_FAST lista
18 LOAD_GLOBAL len
19 LOAD_FAST lista
20 CALL_FUNCTION 1
21 STORE_FAST y
22 LOAD_FAST y
23 LOAD_FAST num
24 BINARY_MULTIPLY 
25 LOAD_CONST 2
26 LOAD_CONST 7
27 BINARY_DIVIDE 
28 BINARY_ADD 
29 LOAD_CONST 4
30 LOAD_CONST 5
31 BINARY_MULTIPLY 
32 LOAD_CONST 2
33 LOAD_CONST 8
34 BINARY_DIVIDE 
35 BINARY_ADD 
36 BINARY_SUBSTRACT 
37 LOAD_CONST 2
38 BINARY_SUBSTRACT 
39 STORE_FAST operacion
40 LOAD_FAST operacion
41 LOAD_CONST 500
42 COMPARE_OP >
43 JUMP_IF_TRUE  54
44 LOAD_FAST operacion
45 LOAD_CONST 5
46 COMPARE_OP ==
47 JUMP_IF_TRUE  51
48 LOAD_CONST "no ok"
49 STORE_FAST proceso
50 JUMP_ABSOLUTE  53
51 LOAD_CONST "ok"
52 STORE_FAST proceso
53 JUMP_ABSOLUTE  77
54 LOAD_GLOBAL fun
55 CALL_FUNCTION 0
56 LOAD_FAST y
57 LOAD_CONST 40
58 COMPARE_OP <=
59 JUMP_IF_FALSE  77
60 LOAD_GLOBAL calcular
61 LOAD_CONST 1
62 LOAD_CONST 2
63 CALL_FUNCTION 2
64 STORE_FAST t
65 LOAD_FAST t
66 LOAD_CONST 5
67 COMPARE_OP ==
68 JUMP_IF_TRUE  72
69 LOAD_CONST 0
70 STORE_FAST paso
71 JUMP_ABSOLUTE  76
72 LOAD_FAST lista
73 LOAD_FAST num
74 BINARY_SUBSCR 
75 STORE_FAST paso
76 JUMP_ABSOLUTE  56
Main
77 LOAD_GLOBAL promedio
78 CALL_FUNCTION 0
